dtwhaclustering/__init__.py
dtwhaclustering/__main__.py
dtwhaclustering/analysis_support.py
dtwhaclustering/dtw_analysis.py
dtwhaclustering/leastSquareModeling.py
dtwhaclustering/plot_linear_trend.py
dtwhaclustering/plot_stations.py
dtwhaclustering-1.0.15.dist-info/LICENSE
dtwhaclustering-1.0.15.dist-info/METADATA
dtwhaclustering-1.0.15.dist-info/WHEEL
dtwhaclustering-1.0.15.dist-info/top_level.txt
dtwhaclustering-1.0.15.dist-info/RECORD
