Metadata-Version: 2.1
Name: dtwhaclustering
Version: 1.0.15
Summary: Codes to perform Dynamic Time Warping Based Hierarchical Agglomerative Clustering of GPS data
Home-page: https://github.com/earthinversion/DTW-based-Hierarchical-Clustering
Author: Utpal Kumar
Author-email: utpalkumar50@gmail.com
License: Apache 2.0
Keywords: dynamic time warping clustering
Platform: UNKNOWN
Classifier: License :: OSI Approved :: Apache Software License
Classifier: Programming Language :: Python :: 3
Requires-Python: >=3.5
License-File: LICENSE
Requires-Dist: dtaidistance
Requires-Dist: matplotlib
Requires-Dist: pygmt
Requires-Dist: pandas
Requires-Dist: numpy
Requires-Dist: xarray
Requires-Dist: tqdm
Provides-Extra: all
Requires-Dist: matplotlib ; extra == 'all'
Requires-Dist: numpy ; extra == 'all'
Requires-Dist: scipy ; extra == 'all'
Requires-Dist: pandas ; extra == 'all'
Requires-Dist: scikit-learn ; extra == 'all'
Requires-Dist: xarray ; extra == 'all'
Provides-Extra: numpy
Requires-Dist: numpy ; extra == 'numpy'
Requires-Dist: scipy ; extra == 'numpy'
Provides-Extra: vis
Requires-Dist: matplotlib ; extra == 'vis'
Requires-Dist: pygmt ; extra == 'vis'
